mindearth/__init__.py
mindearth/setup.py
mindearth/cell/__init__.py
mindearth/cell/activation.py
mindearth/cell/utils.py
mindearth/cell/demnet/__init__.py
mindearth/cell/demnet/demnet.py
mindearth/cell/dgmr/__init__.py
mindearth/cell/dgmr/dgmr.py
mindearth/cell/dgmr/dgmrnet.py
mindearth/cell/graphcast/__init__.py
mindearth/cell/graphcast/graphcast.py
mindearth/cell/graphcast/graphcastnet.py
mindearth/cell/neural_operators/__init__.py
mindearth/cell/neural_operators/afno2d.py
mindearth/cell/neural_operators/afnonet.py
mindearth/cell/neural_operators/dft.py
mindearth/cell/neural_operators/vit_kno.py
mindearth/core/__init__.py
mindearth/core/losses.py
mindearth/core/lr_scheduler.py
mindearth/data/__init__.py
mindearth/data/dataset.py
mindearth/module/__init__.py
mindearth/module/forecast.py
mindearth/module/pretrain.py
mindearth/utils/__init__.py
mindearth/utils/logger.py
mindearth/utils/tools.py
mindearth/utils/visual.py
mindearth/utils/wind_quiver.py
mindearth_gpu-0.2.0.dist-info/METADATA
mindearth_gpu-0.2.0.dist-info/WHEEL
mindearth_gpu-0.2.0.dist-info/top_level.txt
mindearth_gpu-0.2.0.dist-info/RECORD
